{
  "title": "O-Launcher",
  "rules": [
    {
      "description": "O-Launcher",
      "manipulators": [
        {
          "type": "basic",
          "from": {
            "key_code": "a",
            "modifiers": {
              "mandatory": [

              ],
              "optional": [
                "any"
              ]
            }
          },
          "to": [
            {
              "shell_command": "open -a 'Activity Monitor.app'"
            }
          ],
          "conditions": [
            {
              "type": "variable_if",
              "name": "launcher_mode",
              "value": 1
            }
          ]
        },
        {
          "type": "basic",
          "from": {
            "simultaneous": [
              {
                "key_code": "0"
              },
              {
                "key_code": "a"
              }
            ],
            "simultaneous_options": {
              "key_down_order": "strict",
              "key_up_order": "strict_inverse",
              "to_after_key_up": [
                {
                  "set_variable": {
                    "name": "launcher_mode",
                    "value": 0
                  }
                }
              ]
            },
            "modifiers": {
              "mandatory": [

              ],
              "optional": [
                "any"
              ]
            }
          },
          "to": [
            {
              "set_variable": {
                "name": "launcher_mode",
                "value": 1
              }
            },
            {
              "shell_command": "open -a 'Activity Monitor.app'"
            }
          ],
          "parameters": {
            "basic.simultaneous_threshold_milliseconds": 500
          }
        },
        {
          "type": "basic",
          "from": {
            "key_code": "b",
            "modifiers": {
              "mandatory": [

              ],
              "optional": [
                "any"
              ]
            }
          },
          "to": [
            {
              "shell_command": "open -a 'Google Chrome.app'"
            }
          ],
          "conditions": [
            {
              "type": "variable_if",
              "name": "launcher_mode",
              "value": 1
            }
          ]
        },
        {
          "type": "basic",
          "from": {
            "simultaneous": [
              {
                "key_code": "0"
              },
              {
                "key_code": "b"
              }
            ],
            "simultaneous_options": {
              "key_down_order": "strict",
              "key_up_order": "strict_inverse",
              "to_after_key_up": [
                {
                  "set_variable": {
                    "name": "launcher_mode",
                    "value": 0
                  }
                }
              ]
            },
            "modifiers": {
              "mandatory": [

              ],
              "optional": [
                "any"
              ]
            }
          },
          "to": [
            {
              "set_variable": {
                "name": "launcher_mode",
                "value": 1
              }
            },
            {
              "shell_command": "open -a 'Google Chrome.app'"
            }
          ],
          "parameters": {
            "basic.simultaneous_threshold_milliseconds": 500
          }
        },
        {
          "type": "basic",
          "from": {
            "key_code": "c",
            "modifiers": {
              "mandatory": [

              ],
              "optional": [
                "any"
              ]
            }
          },
          "to": [
            {
              "shell_command": "open -a 'Visual Studio Code.app'"
            }
          ],
          "conditions": [
            {
              "type": "variable_if",
              "name": "launcher_mode",
              "value": 1
            }
          ]
        },
        {
          "type": "basic",
          "from": {
            "simultaneous": [
              {
                "key_code": "0"
              },
              {
                "key_code": "c"
              }
            ],
            "simultaneous_options": {
              "key_down_order": "strict",
              "key_up_order": "strict_inverse",
              "to_after_key_up": [
                {
                  "set_variable": {
                    "name": "launcher_mode",
                    "value": 0
                  }
                }
              ]
            },
            "modifiers": {
              "mandatory": [

              ],
              "optional": [
                "any"
              ]
            }
          },
          "to": [
            {
              "set_variable": {
                "name": "launcher_mode",
                "value": 1
              }
            },
            {
              "shell_command": "open -a 'Visual Studio Code.app'"
            }
          ],
          "parameters": {
            "basic.simultaneous_threshold_milliseconds": 500
          }
        },
        {
          "type": "basic",
          "from": {
            "key_code": "f",
            "modifiers": {
              "mandatory": [

              ],
              "optional": [
                "any"
              ]
            }
          },
          "to": [
            {
              "shell_command": "open -a 'Finder.app'"
            }
          ],
          "conditions": [
            {
              "type": "variable_if",
              "name": "launcher_mode",
              "value": 1
            }
          ]
        },
        {
          "type": "basic",
          "from": {
            "simultaneous": [
              {
                "key_code": "0"
              },
              {
                "key_code": "f"
              }
            ],
            "simultaneous_options": {
              "key_down_order": "strict",
              "key_up_order": "strict_inverse",
              "to_after_key_up": [
                {
                  "set_variable": {
                    "name": "launcher_mode",
                    "value": 0
                  }
                }
              ]
            },
            "modifiers": {
              "mandatory": [

              ],
              "optional": [
                "any"
              ]
            }
          },
          "to": [
            {
              "set_variable": {
                "name": "launcher_mode",
                "value": 1
              }
            },
            {
              "shell_command": "open -a 'Finder.app'"
            }
          ],
          "parameters": {
            "basic.simultaneous_threshold_milliseconds": 500
          }
        },
        {
          "type": "basic",
          "from": {
            "key_code": "i",
            "modifiers": {
              "mandatory": [

              ],
              "optional": [
                "any"
              ]
            }
          },
          "to": [
            {
              "shell_command": "open -a 'iTerm.app'"
            }
          ],
          "conditions": [
            {
              "type": "variable_if",
              "name": "launcher_mode",
              "value": 1
            }
          ]
        },
        {
          "type": "basic",
          "from": {
            "simultaneous": [
              {
                "key_code": "0"
              },
              {
                "key_code": "i"
              }
            ],
            "simultaneous_options": {
              "key_down_order": "strict",
              "key_up_order": "strict_inverse",
              "to_after_key_up": [
                {
                  "set_variable": {
                    "name": "launcher_mode",
                    "value": 0
                  }
                }
              ]
            },
            "modifiers": {
              "mandatory": [

              ],
              "optional": [
                "any"
              ]
            }
          },
          "to": [
            {
              "set_variable": {
                "name": "launcher_mode",
                "value": 1
              }
            },
            {
              "shell_command": "open -a 'iTerm.app'"
            }
          ],
          "parameters": {
            "basic.simultaneous_threshold_milliseconds": 500
          }
        },
        {
          "type": "basic",
          "from": {
            "key_code": "k",
            "modifiers": {
              "mandatory": [

              ],
              "optional": [
                "any"
              ]
            }
          },
          "to": [
            {
              "shell_command": "open -a 'KeePassXC.app'"
            }
          ],
          "conditions": [
            {
              "type": "variable_if",
              "name": "launcher_mode",
              "value": 1
            }
          ]
        },
        {
          "type": "basic",
          "from": {
            "simultaneous": [
              {
                "key_code": "0"
              },
              {
                "key_code": "k"
              }
            ],
            "simultaneous_options": {
              "key_down_order": "strict",
              "key_up_order": "strict_inverse",
              "to_after_key_up": [
                {
                  "set_variable": {
                    "name": "launcher_mode",
                    "value": 0
                  }
                }
              ]
            },
            "modifiers": {
              "mandatory": [

              ],
              "optional": [
                "any"
              ]
            }
          },
          "to": [
            {
              "set_variable": {
                "name": "launcher_mode",
                "value": 1
              }
            },
            {
              "shell_command": "open -a 'KeePassXC.app'"
            }
          ],
          "parameters": {
            "basic.simultaneous_threshold_milliseconds": 500
          }
        },
        {
          "type": "basic",
          "from": {
            "key_code": "p",
            "modifiers": {
              "mandatory": [

              ],
              "optional": [
                "any"
              ]
            }
          },
          "to": [
            {
              "shell_command": "open -a 'Opera.app'"
            }
          ],
          "conditions": [
            {
              "type": "variable_if",
              "name": "launcher_mode",
              "value": 1
            }
          ]
        },
        {
          "type": "basic",
          "from": {
            "simultaneous": [
              {
                "key_code": "0"
              },
              {
                "key_code": "p"
              }
            ],
            "simultaneous_options": {
              "key_down_order": "strict",
              "key_up_order": "strict_inverse",
              "to_after_key_up": [
                {
                  "set_variable": {
                    "name": "launcher_mode",
                    "value": 0
                  }
                }
              ]
            },
            "modifiers": {
              "mandatory": [

              ],
              "optional": [
                "any"
              ]
            }
          },
          "to": [
            {
              "set_variable": {
                "name": "launcher_mode",
                "value": 1
              }
            },
            {
              "shell_command": "open -a 'Opera.app'"
            }
          ],
          "parameters": {
            "basic.simultaneous_threshold_milliseconds": 500
          }
        },
        {
          "type": "basic",
          "from": {
            "key_code": "s",
            "modifiers": {
              "mandatory": [

              ],
              "optional": [
                "any"
              ]
            }
          },
          "to": [
            {
              "shell_command": "open -a 'Slack.app'"
            }
          ],
          "conditions": [
            {
              "type": "variable_if",
              "name": "launcher_mode",
              "value": 1
            }
          ]
        },
        {
          "type": "basic",
          "from": {
            "simultaneous": [
              {
                "key_code": "0"
              },
              {
                "key_code": "s"
              }
            ],
            "simultaneous_options": {
              "key_down_order": "strict",
              "key_up_order": "strict_inverse",
              "to_after_key_up": [
                {
                  "set_variable": {
                    "name": "launcher_mode",
                    "value": 0
                  }
                }
              ]
            },
            "modifiers": {
              "mandatory": [

              ],
              "optional": [
                "any"
              ]
            }
          },
          "to": [
            {
              "set_variable": {
                "name": "launcher_mode",
                "value": 1
              }
            },
            {
              "shell_command": "open -a 'Slack.app'"
            }
          ],
          "parameters": {
            "basic.simultaneous_threshold_milliseconds": 500
          }
        },
        {
          "type": "basic",
          "from": {
            "key_code": "v",
            "modifiers": {
              "mandatory": [

              ],
              "optional": [
                "any"
              ]
            }
          },
          "to": [
            {
              "shell_command": "open -a 'Cisco AnyConnect Secure Mobility Client.app'"
            }
          ],
          "conditions": [
            {
              "type": "variable_if",
              "name": "launcher_mode",
              "value": 1
            }
          ]
        },
        {
          "type": "basic",
          "from": {
            "simultaneous": [
              {
                "key_code": "0"
              },
              {
                "key_code": "v"
              }
            ],
            "simultaneous_options": {
              "key_down_order": "strict",
              "key_up_order": "strict_inverse",
              "to_after_key_up": [
                {
                  "set_variable": {
                    "name": "launcher_mode",
                    "value": 0
                  }
                }
              ]
            },
            "modifiers": {
              "mandatory": [

              ],
              "optional": [
                "any"
              ]
            }
          },
          "to": [
            {
              "set_variable": {
                "name": "launcher_mode",
                "value": 1
              }
            },
            {
              "shell_command": "open -a 'Cisco AnyConnect Secure Mobility Client.app'"
            }
          ],
          "parameters": {
            "basic.simultaneous_threshold_milliseconds": 500
          }
        }
      ]
    }
  ]
}
